odoo9_addon_project_task_report-9.0.1.1.0-py2.7-nspkg.pth
odoo9_addon_project_task_report-9.0.1.1.0.dist-info/DESCRIPTION.rst
odoo9_addon_project_task_report-9.0.1.1.0.dist-info/METADATA
odoo9_addon_project_task_report-9.0.1.1.0.dist-info/RECORD
odoo9_addon_project_task_report-9.0.1.1.0.dist-info/WHEEL
odoo9_addon_project_task_report-9.0.1.1.0.dist-info/metadata.json
odoo9_addon_project_task_report-9.0.1.1.0.dist-info/namespace_packages.txt
odoo9_addon_project_task_report-9.0.1.1.0.dist-info/top_level.txt
odoo_addons/project_task_report/README.rst
odoo_addons/project_task_report/__init__.py
odoo_addons/project_task_report/__openerp__.py
odoo_addons/project_task_report/i18n/es.po
odoo_addons/project_task_report/i18n/fr.po
odoo_addons/project_task_report/static/description/icon.png
odoo_addons/project_task_report/views/project_task_chatter_report.xml
odoo_addons/project_task_report/views/project_task_report.xml
